{
  "ts": 1776300378367,
  "count": 5,
  "results": [
    {
      "key": "slack_setup",
      "q": "슬랙 워크플로우",
      "cat": "슬랙",
      "autoFitGuess": 5,
      "totalReviews": 5770,
      "top3Share": 0.43830155979202773,
      "median": 90000,
      "avg": 92600,
      "min": 29000,
      "max": 290000,
      "passDemand": true,
      "passComp": true,
      "passPrice": false,
      "passAuto": true,
      "allPass": false,
      "scannedAt": "2026-04-16T00:45:47.757Z"
    },
    {
      "key": "discord_bot",
      "q": "디스코드 봇",
      "cat": "디스코드봇",
      "autoFitGuess": 5,
      "totalReviews": 851,
      "top3Share": 0.6145710928319624,
      "median": 500000,
      "avg": 266700,
      "min": 8000,
      "max": 500000,
      "passDemand": true,
      "passComp": false,
      "passPrice": true,
      "passAuto": true,
      "allPass": false,
      "scannedAt": "2026-04-16T00:45:54.628Z"
    },
    {
      "key": "line_bot",
      "q": "라인 봇",
      "cat": "라인봇",
      "autoFitGuess": 5,
      "totalReviews": 98,
      "top3Share": 0.336734693877551,
      "median": 10000,
      "avg": 198462,
      "min": 10000,
      "max": 500000,
      "passDemand": false,
      "passComp": true,
      "passPrice": false,
      "passAuto": true,
      "allPass": false,
      "scannedAt": "2026-04-16T00:46:01.389Z"
    },
    {
      "key": "linkedin_mkt",
      "q": "링크드인 마케팅",
      "cat": "링크드인",
      "autoFitGuess": 3,
      "totalReviews": 42,
      "top3Share": 0.2857142857142857,
      "median": 5000,
      "avg": 124750,
      "min": 5000,
      "max": 1000000,
      "passDemand": false,
      "passComp": true,
      "passPrice": false,
      "passAuto": false,
      "allPass": false,
      "scannedAt": "2026-04-16T00:46:08.869Z"
    },
    {
      "key": "twitter_mkt",
      "q": "트위터 마케팅",
      "cat": "트위터",
      "autoFitGuess": 3,
      "totalReviews": 5841,
      "top3Share": 0.3518233179250128,
      "median": 5000,
      "avg": 22450,
      "min": 5000,
      "max": 200000,
      "passDemand": true,
      "passComp": true,
      "passPrice": false,
      "passAuto": false,
      "allPass": false,
      "scannedAt": "2026-04-16T00:46:15.731Z"
    }
  ]
}