{
  "ts": 1776304017411,
  "count": 5,
  "results": [
    {
      "key": "tiktok_mkt",
      "q": "틱톡 마케팅",
      "cat": "틱톡",
      "autoFitGuess": 3,
      "totalReviews": 824,
      "top3Share": 0.47936893203883496,
      "median": 5000,
      "avg": 132250,
      "min": 5000,
      "max": 990000,
      "passDemand": true,
      "passComp": true,
      "passPrice": false,
      "passAuto": false,
      "allPass": false,
      "scannedAt": "2026-04-16T01:46:27.069Z"
    },
    {
      "key": "shorts_edit",
      "q": "쇼츠 편집",
      "cat": "쇼츠편집",
      "autoFitGuess": 4,
      "totalReviews": 1643,
      "top3Share": 0.5027388922702374,
      "median": 33000,
      "avg": 80200,
      "min": 5000,
      "max": 400000,
      "passDemand": true,
      "passComp": true,
      "passPrice": false,
      "passAuto": true,
      "allPass": false,
      "scannedAt": "2026-04-16T01:46:33.932Z"
    },
    {
      "key": "reels_edit",
      "q": "릴스 편집",
      "cat": "릴스편집",
      "autoFitGuess": 4,
      "totalReviews": 2778,
      "top3Share": 0.5237580993520519,
      "median": 60000,
      "avg": 85300,
      "min": 5000,
      "max": 400000,
      "passDemand": true,
      "passComp": true,
      "passPrice": false,
      "passAuto": true,
      "allPass": false,
      "scannedAt": "2026-04-16T01:46:40.870Z"
    },
    {
      "key": "podcast_edit",
      "q": "팟캐스트 편집",
      "cat": "팟캐스트",
      "autoFitGuess": 4,
      "totalReviews": 65,
      "top3Share": 0.6,
      "median": 10000,
      "avg": 10000,
      "min": 10000,
      "max": 10000,
      "passDemand": false,
      "passComp": false,
      "passPrice": false,
      "passAuto": true,
      "allPass": false,
      "scannedAt": "2026-04-16T01:46:47.938Z"
    },
    {
      "key": "educational_video",
      "q": "강의 영상 제작",
      "cat": "강의영상",
      "autoFitGuess": 3,
      "totalReviews": 3067,
      "top3Share": 0.6944897293772416,
      "median": 330000,
      "avg": 269050,
      "min": 5000,
      "max": 990000,
      "passDemand": true,
      "passComp": false,
      "passPrice": true,
      "passAuto": false,
      "allPass": false,
      "scannedAt": "2026-04-16T01:46:54.808Z"
    }
  ]
}